gen_nasm/__init__.py
gen_nasm/py.typed
gen_nasm/conf/gen_nasm.cfg
gen_nasm/conf/gen_nasm.logo
gen_nasm/conf/gen_nasm_util.cfg
gen_nasm/conf/project.yaml
gen_nasm/conf/template/asmflags.template
gen_nasm/conf/template/ldflags.template
gen_nasm/conf/template/main.template
gen_nasm/conf/template/objects.template
gen_nasm/conf/template/sources.template
gen_nasm/log/gen_nasm.log
gen_nasm/pro/__init__.py
gen_nasm/pro/read_template.py
gen_nasm/pro/write_template.py
usr/local/bin/gen_nasm_run.py
gen_nasm-1.0.2.dist-info/LICENSE
gen_nasm-1.0.2.dist-info/METADATA
gen_nasm-1.0.2.dist-info/WHEEL
gen_nasm-1.0.2.dist-info/top_level.txt
gen_nasm-1.0.2.dist-info/RECORD
